creality_wifi_box_client/__init__.py
creality_wifi_box_client/box_info.py
creality_wifi_box_client/creality_wifi_box_client.py
creality_wifi_box_client/exceptions.py
creality_wifi_box_client-0.1.0.dist-info/licenses/LICENSE
tests/__init__.py
tests/test_box_info.py
tests/test_creality_wifi_box_client.py
tests/test_exceptions.py
creality_wifi_box_client-0.1.0.dist-info/METADATA
creality_wifi_box_client-0.1.0.dist-info/WHEEL
creality_wifi_box_client-0.1.0.dist-info/top_level.txt
creality_wifi_box_client-0.1.0.dist-info/RECORD
