Metadata-Version: 2.4
Name: creality_wifi_box_client
Version: 0.1.0
Summary: Client for Creality Wifi Box
Author-email: Patrick Cartwright <pcartwright1981@gmail.com>
License: MIT License
Project-URL: Repository, https://github.com/pcartwright81/creality_wifi_box_client
Classifier: Programming Language :: Python :: 3
Classifier: License :: OSI Approved :: MIT License
Classifier: Operating System :: OS Independent
License-File: LICENSE
Requires-Dist: aiohttp==3.13.2
Requires-Dist: colorlog==6.10.1
Requires-Dist: pydantic
Provides-Extra: test
Requires-Dist: pytest==9.0.2; extra == "test"
Requires-Dist: pytest-asyncio==1.3.0; extra == "test"
Requires-Dist: pytest-cov==7.0.0; extra == "test"
Provides-Extra: dev
Requires-Dist: ruff==0.14.9; extra == "dev"
Dynamic: license-file
